nalyst/__init__.py
nalyst/exceptions.py
nalyst/automl/__init__.py
nalyst/automl/classification.py
nalyst/automl/experiment.py
nalyst/automl/regression.py
nalyst/automl/tuning.py
nalyst/calibration/__init__.py
nalyst/calibration/calibrators.py
nalyst/calibration/curves.py
nalyst/clustering/__init__.py
nalyst/clustering/density.py
nalyst/clustering/extra.py
nalyst/clustering/hierarchical.py
nalyst/clustering/kmeans.py
nalyst/clustering/spectral.py
nalyst/core/__init__.py
nalyst/core/foundation.py
nalyst/core/settings.py
nalyst/core/tags.py
nalyst/core/validation.py
nalyst/covariance/__init__.py
nalyst/covariance/empirical.py
nalyst/covariance/robust.py
nalyst/covariance/shrunk.py
nalyst/datasets/__init__.py
nalyst/datasets/base.py
nalyst/datasets/generators.py
nalyst/datasets/loaders.py
nalyst/diagnostics/__init__.py
nalyst/diagnostics/autocorrelation.py
nalyst/diagnostics/heteroscedasticity.py
nalyst/diagnostics/multicollinearity.py
nalyst/diagnostics/residuals.py
nalyst/diagnostics/specification.py
nalyst/discriminant/__init__.py
nalyst/discriminant/lda.py
nalyst/discriminant/qda.py
nalyst/evaluation/__init__.py
nalyst/evaluation/search.py
nalyst/evaluation/splitting.py
nalyst/evaluation/validation.py
nalyst/explainability/__init__.py
nalyst/explainability/feature_importance.py
nalyst/explainability/lime_explain.py
nalyst/explainability/shap_explain.py
nalyst/gam/__init__.py
nalyst/gam/core.py
nalyst/gam/terms.py
nalyst/gaussian_process/__init__.py
nalyst/gaussian_process/gpc.py
nalyst/gaussian_process/gpr.py
nalyst/gaussian_process/kernels.py
nalyst/glm/__init__.py
nalyst/glm/families.py
nalyst/glm/glm.py
nalyst/glm/links.py
nalyst/imbalance/__init__.py
nalyst/imbalance/combined.py
nalyst/imbalance/oversampling.py
nalyst/imbalance/undersampling.py
nalyst/inspection/__init__.py
nalyst/inspection/importance.py
nalyst/inspection/partial_dependence.py
nalyst/learners/__init__.py
nalyst/learners/ensemble/__init__.py
nalyst/learners/ensemble/bagging.py
nalyst-2.0.5.dist-info/licenses/LICENSE
nalyst-2.0.5.dist-info/METADATA
nalyst-2.0.5.dist-info/WHEEL
nalyst-2.0.5.dist-info/top_level.txt
nalyst-2.0.5.dist-info/RECORD
