Metadata-Version: 2.4
Name: nalyst
Version: 2.0.5
Summary: Full-stack machine learning, statistics, time series, survival, and deep learning toolkit with a unified train/infer API, AutoML, explainability, and diagnostics
Author: Hemant Thapa
Author-email: hemantthapa1998@gmail.com
Maintainer: Hemant Thapa
Maintainer-email: hemantthapa1998@gmail.com
License: MIT
Keywords: machine learning,artificial intelligence,deep learning,data science,neural networks,predictive modeling,statistical learning
Classifier: Development Status :: 5 - Production/Stable
Classifier: Intended Audience :: Developers
Classifier: Intended Audience :: Science/Research
Classifier: Programming Language :: Python :: 3
Classifier: Programming Language :: Python :: 3.10
Classifier: Programming Language :: Python :: 3.11
Classifier: Programming Language :: Python :: 3.12
Classifier: Programming Language :: Python :: 3.13
Classifier: Topic :: Scientific/Engineering :: Artificial Intelligence
Classifier: Topic :: Scientific/Engineering :: Mathematics
Classifier: Operating System :: OS Independent
Requires-Python: >=3.10
License-File: LICENSE
Requires-Dist: numpy>=1.24.0
Requires-Dist: scipy>=1.10.0
Requires-Dist: joblib>=1.3.0
Requires-Dist: threadpoolctl>=3.0.0
Provides-Extra: dev
Requires-Dist: pytest>=7.0.0; extra == "dev"
Requires-Dist: pytest-cov>=4.0.0; extra == "dev"
Requires-Dist: ruff>=0.1.0; extra == "dev"
Requires-Dist: mypy>=1.0.0; extra == "dev"
Provides-Extra: visualization
Requires-Dist: matplotlib>=3.6.0; extra == "visualization"
Requires-Dist: seaborn>=0.12.0; extra == "visualization"
Requires-Dist: plotly>=5.10.0; extra == "visualization"
Provides-Extra: dataframes
Requires-Dist: pandas>=2.0.0; extra == "dataframes"
Requires-Dist: polars>=0.19.0; extra == "dataframes"
Provides-Extra: all
Requires-Dist: matplotlib>=3.6.0; extra == "all"
Requires-Dist: seaborn>=0.12.0; extra == "all"
Requires-Dist: plotly>=5.10.0; extra == "all"
Requires-Dist: pandas>=2.0.0; extra == "all"
Requires-Dist: polars>=0.19.0; extra == "all"
Requires-Dist: pytest>=7.0.0; extra == "all"
Requires-Dist: pytest-cov>=4.0.0; extra == "all"
Requires-Dist: ruff>=0.1.0; extra == "all"
Requires-Dist: mypy>=1.0.0; extra == "all"
Dynamic: license-file
